{
  "ran_at": "2026-05-05T10:29:15+00:00",
  "duckdb_available": true,
  "total_rules": 72,
  "passed": 29,
  "failed": 2,
  "errored": 0,
  "pending": 41,
  "pass_rate": 0.9355,
  "by_severity": {
    "critical": {
      "passed": 13,
      "failed": 0,
      "errored": 0,
      "pending": 15
    },
    "high": {
      "passed": 10,
      "failed": 1,
      "errored": 0,
      "pending": 16
    },
    "medium": {
      "passed": 6,
      "failed": 1,
      "errored": 0,
      "pending": 10
    }
  },
  "by_subdomain": {
    "payments": {
      "passed": 6,
      "failed": 1,
      "errored": 0,
      "pending": 0
    },
    "p_and_c_claims": {
      "passed": 5,
      "failed": 0,
      "errored": 0,
      "pending": 0
    },
    "demand_planning": {
      "passed": 4,
      "failed": 0,
      "errored": 0,
      "pending": 0
    },
    "hotel_revenue_management": {
      "passed": 4,
      "failed": 0,
      "errored": 0,
      "pending": 0
    },
    "merchandising": {
      "passed": 4,
      "failed": 0,
      "errored": 0,
      "pending": 0
    },
    "mes_quality": {
      "passed": 2,
      "failed": 1,
      "errored": 0,
      "pending": 0
    },
    "pharmacovigilance": {
      "passed": 4,
      "failed": 0,
      "errored": 0,
      "pending": 0
    },
    "ehr_integrations": {
      "passed": 0,
      "failed": 0,
      "errored": 0,
      "pending": 5
    },
    "capital_markets": {
      "passed": 0,
      "failed": 0,
      "errored": 0,
      "pending": 4
    },
    "smart_metering": {
      "passed": 0,
      "failed": 0,
      "errored": 0,
      "pending": 4
    },
    "clinical_trials": {
      "passed": 0,
      "failed": 0,
      "errored": 0,
      "pending": 4
    },
    "cloud_finops": {
      "passed": 0,
      "failed": 0,
      "errored": 0,
      "pending": 4
    },
    "ev_charging": {
      "passed": 0,
      "failed": 0,
      "errored": 0,
      "pending": 4
    },
    "tax_administration": {
      "passed": 0,
      "failed": 0,
      "errored": 0,
      "pending": 4
    },
    "real_world_evidence": {
      "passed": 0,
      "failed": 0,
      "errored": 0,
      "pending": 4
    },
    "settlement_clearing": {
      "passed": 0,
      "failed": 0,
      "errored": 0,
      "pending": 4
    },
    "programmatic_advertising": {
      "passed": 0,
      "failed": 0,
      "errored": 0,
      "pending": 4
    }
  },
  "results": [
    {
      "id": "dq_payments_001",
      "subdomain": "payments",
      "table": "payments.payments",
      "column": "amount",
      "rule_type": "not_null",
      "severity": "critical",
      "expectation": "amount must be non-null on every payment",
      "failing_rows": 0,
      "passed": true,
      "duration_ms": 0,
      "error": null
    },
    {
      "id": "dq_payments_002",
      "subdomain": "payments",
      "table": "payments.payments",
      "column": "payment_id",
      "rule_type": "uniqueness",
      "severity": "critical",
      "expectation": "payment_id is unique across the payments table",
      "failing_rows": 0,
      "passed": true,
      "duration_ms": 17,
      "error": null
    },
    {
      "id": "dq_payments_003",
      "subdomain": "payments",
      "table": "payments.payments",
      "column": "amount",
      "rule_type": "range",
      "severity": "high",
      "expectation": "amount strictly positive for completed payments",
      "failing_rows": 0,
      "passed": true,
      "duration_ms": 0,
      "error": null
    },
    {
      "id": "dq_payments_004",
      "subdomain": "payments",
      "table": "payments.payments",
      "column": "rail",
      "rule_type": "distribution",
      "severity": "high",
      "expectation": "rail values are in the allowed enum {card, ach, wire, rtp} — flags drift e.g. SEPA volume",
      "failing_rows": 9942,
      "passed": false,
      "duration_ms": 3,
      "error": null
    },
    {
      "id": "dq_payments_005",
      "subdomain": "payments",
      "table": "payments.payments",
      "column": "merchant_id",
      "rule_type": "foreign_key",
      "severity": "critical",
      "expectation": "every payments.merchant_id resolves in payments.merchants",
      "failing_rows": 0,
      "passed": true,
      "duration_ms": 12,
      "error": null
    },
    {
      "id": "dq_payments_006",
      "subdomain": "payments",
      "table": "payments.settlements",
      "column": "settled_at",
      "rule_type": "freshness",
      "severity": "high",
      "expectation": "no settlements dated in the future relative to most-recent auth",
      "failing_rows": 0,
      "passed": true,
      "duration_ms": 0,
      "error": null
    },
    {
      "id": "dq_payments_007",
      "subdomain": "payments",
      "table": "payments.disputes",
      "column": "amount",
      "rule_type": "not_null",
      "severity": "high",
      "expectation": "dispute amount captured for every dispute",
      "failing_rows": 0,
      "passed": true,
      "duration_ms": 0,
      "error": null
    },
    {
      "id": "dq_claims_001",
      "subdomain": "p_and_c_claims",
      "table": "p_and_c_claims.claims",
      "column": "claim_id",
      "rule_type": "uniqueness",
      "severity": "critical",
      "expectation": "claim_id is unique",
      "failing_rows": 0,
      "passed": true,
      "duration_ms": 8,
      "error": null
    },
    {
      "id": "dq_claims_002",
      "subdomain": "p_and_c_claims",
      "table": "p_and_c_claims.claims",
      "column": "incurred_amount",
      "rule_type": "range",
      "severity": "high",
      "expectation": "incurred amount must be non-negative",
      "failing_rows": 0,
      "passed": true,
      "duration_ms": 0,
      "error": null
    },
    {
      "id": "dq_claims_003",
      "subdomain": "p_and_c_claims",
      "table": "p_and_c_claims.claims",
      "column": "policy_id",
      "rule_type": "foreign_key",
      "severity": "critical",
      "expectation": "every claim has a resolvable policy",
      "failing_rows": 0,
      "passed": true,
      "duration_ms": 7,
      "error": null
    },
    {
      "id": "dq_claims_004",
      "subdomain": "p_and_c_claims",
      "table": "p_and_c_claims.claims",
      "column": "status",
      "rule_type": "distribution",
      "severity": "medium",
      "expectation": "claim status is in {open, closed_paid, closed_denied, in_litigation}",
      "failing_rows": 0,
      "passed": true,
      "duration_ms": 2,
      "error": null
    },
    {
      "id": "dq_claims_005",
      "subdomain": "p_and_c_claims",
      "table": "p_and_c_claims.claims",
      "column": "loss_date",
      "rule_type": "freshness",
      "severity": "medium",
      "expectation": "loss_date no more than 1 day in the future",
      "failing_rows": 0,
      "passed": true,
      "duration_ms": 0,
      "error": null
    },
    {
      "id": "dq_demand_001",
      "subdomain": "demand_planning",
      "table": "demand_planning.forecasts",
      "column": "forecast_qty",
      "rule_type": "range",
      "severity": "high",
      "expectation": "forecast_qty non-negative",
      "failing_rows": 0,
      "passed": true,
      "duration_ms": 0,
      "error": null
    },
    {
      "id": "dq_demand_002",
      "subdomain": "demand_planning",
      "table": "demand_planning.forecasts",
      "column": "forecast_id",
      "rule_type": "uniqueness",
      "severity": "critical",
      "expectation": "forecast_id is unique",
      "failing_rows": 0,
      "passed": true,
      "duration_ms": 7,
      "error": null
    },
    {
      "id": "dq_demand_003",
      "subdomain": "demand_planning",
      "table": "demand_planning.forecast_errors",
      "column": "forecast_id",
      "rule_type": "foreign_key",
      "severity": "critical",
      "expectation": "every error row points to a real forecast",
      "failing_rows": 0,
      "passed": true,
      "duration_ms": 12,
      "error": null
    },
    {
      "id": "dq_demand_004",
      "subdomain": "demand_planning",
      "table": "demand_planning.historical_demand",
      "column": "quantity",
      "rule_type": "range",
      "severity": "medium",
      "expectation": "historical quantity non-negative",
      "failing_rows": 0,
      "passed": true,
      "duration_ms": 0,
      "error": null
    },
    {
      "id": "dq_hotel_001",
      "subdomain": "hotel_revenue_management",
      "table": "hotel_revenue_management.reservations",
      "column": "arrival_date",
      "rule_type": "not_null",
      "severity": "critical",
      "expectation": "arrival_date populated for every reservation",
      "failing_rows": 0,
      "passed": true,
      "duration_ms": 0,
      "error": null
    },
    {
      "id": "dq_hotel_002",
      "subdomain": "hotel_revenue_management",
      "table": "hotel_revenue_management.reservations",
      "column": "nights",
      "rule_type": "range",
      "severity": "high",
      "expectation": "nights between 1 and 90 inclusive",
      "failing_rows": 0,
      "passed": true,
      "duration_ms": 0,
      "error": null
    },
    {
      "id": "dq_hotel_003",
      "subdomain": "hotel_revenue_management",
      "table": "hotel_revenue_management.daily_pricing",
      "column": "rate",
      "rule_type": "range",
      "severity": "high",
      "expectation": "daily rate strictly positive",
      "failing_rows": 0,
      "passed": true,
      "duration_ms": 0,
      "error": null
    },
    {
      "id": "dq_hotel_004",
      "subdomain": "hotel_revenue_management",
      "table": "hotel_revenue_management.reservations",
      "column": "rate_plan_id",
      "rule_type": "foreign_key",
      "severity": "critical",
      "expectation": "rate_plan_id resolves in rate_plans",
      "failing_rows": 0,
      "passed": true,
      "duration_ms": 8,
      "error": null
    },
    {
      "id": "dq_merch_001",
      "subdomain": "merchandising",
      "table": "merchandising.sales_lines",
      "column": "extended_amount",
      "rule_type": "range",
      "severity": "high",
      "expectation": "extended_amount non-negative",
      "failing_rows": 0,
      "passed": true,
      "duration_ms": 0,
      "error": null
    },
    {
      "id": "dq_merch_002",
      "subdomain": "merchandising",
      "table": "merchandising.products",
      "column": "sku",
      "rule_type": "uniqueness",
      "severity": "critical",
      "expectation": "sku is unique in products",
      "failing_rows": 0,
      "passed": true,
      "duration_ms": 3,
      "error": null
    },
    {
      "id": "dq_merch_003",
      "subdomain": "merchandising",
      "table": "merchandising.sales_lines",
      "column": "sku",
      "rule_type": "foreign_key",
      "severity": "critical",
      "expectation": "every sale resolves to a product",
      "failing_rows": 0,
      "passed": true,
      "duration_ms": 19,
      "error": null
    },
    {
      "id": "dq_merch_004",
      "subdomain": "merchandising",
      "table": "merchandising.prices",
      "column": "list_price",
      "rule_type": "range",
      "severity": "medium",
      "expectation": "list_price strictly positive",
      "failing_rows": 0,
      "passed": true,
      "duration_ms": 0,
      "error": null
    },
    {
      "id": "dq_mes_001",
      "subdomain": "mes_quality",
      "table": "mes_quality.work_orders",
      "column": "qty_produced",
      "rule_type": "range",
      "severity": "medium",
      "expectation": "qty_produced does not exceed qty_planned by more than 10%",
      "failing_rows": 4496,
      "passed": false,
      "duration_ms": 2,
      "error": null
    },
    {
      "id": "dq_mes_002",
      "subdomain": "mes_quality",
      "table": "mes_quality.sensor_readings",
      "column": "value",
      "rule_type": "not_null",
      "severity": "high",
      "expectation": "sensor reading value populated",
      "failing_rows": 0,
      "passed": true,
      "duration_ms": 0,
      "error": null
    },
    {
      "id": "dq_mes_003",
      "subdomain": "mes_quality",
      "table": "mes_quality.defects",
      "column": "severity",
      "rule_type": "distribution",
      "severity": "medium",
      "expectation": "defect severity is in {minor, major, critical}",
      "failing_rows": 0,
      "passed": true,
      "duration_ms": 2,
      "error": null
    },
    {
      "id": "dq_pv_001",
      "subdomain": "pharmacovigilance",
      "table": "pharmacovigilance.cases",
      "column": "case_id",
      "rule_type": "uniqueness",
      "severity": "critical",
      "expectation": "case_id is unique",
      "failing_rows": 0,
      "passed": true,
      "duration_ms": 8,
      "error": null
    },
    {
      "id": "dq_pv_002",
      "subdomain": "pharmacovigilance",
      "table": "pharmacovigilance.cases",
      "column": "seriousness",
      "rule_type": "distribution",
      "severity": "high",
      "expectation": "seriousness in {serious, non_serious, life_threatening, death}",
      "failing_rows": 0,
      "passed": true,
      "duration_ms": 2,
      "error": null
    },
    {
      "id": "dq_pv_003",
      "subdomain": "pharmacovigilance",
      "table": "pharmacovigilance.adverse_events",
      "column": "case_id",
      "rule_type": "foreign_key",
      "severity": "critical",
      "expectation": "every adverse event maps to a case",
      "failing_rows": 0,
      "passed": true,
      "duration_ms": 19,
      "error": null
    },
    {
      "id": "dq_pv_004",
      "subdomain": "pharmacovigilance",
      "table": "pharmacovigilance.cases",
      "column": "received_at",
      "rule_type": "freshness",
      "severity": "medium",
      "expectation": "received_at not in the future",
      "failing_rows": 0,
      "passed": true,
      "duration_ms": 0,
      "error": null
    },
    {
      "id": "dq_ehr_001",
      "subdomain": "ehr_integrations",
      "table": "ehr_integrations.patient",
      "column": "patient_id",
      "rule_type": "not_null",
      "severity": "critical",
      "expectation": "FHIR Patient.id is required on every patient row",
      "failing_rows": 0,
      "passed": false,
      "duration_ms": 0,
      "error": null,
      "status": "pending — awaiting data generation",
      "count": null
    },
    {
      "id": "dq_ehr_002",
      "subdomain": "ehr_integrations",
      "table": "ehr_integrations.patient",
      "column": "patient_id",
      "rule_type": "uniqueness",
      "severity": "critical",
      "expectation": "patient_id is unique across ehr_integrations.patient",
      "failing_rows": 0,
      "passed": false,
      "duration_ms": 0,
      "error": null,
      "status": "pending — awaiting data generation",
      "count": null
    },
    {
      "id": "dq_ehr_003",
      "subdomain": "ehr_integrations",
      "table": "ehr_integrations.observation",
      "column": "patient_id",
      "rule_type": "foreign_key",
      "severity": "critical",
      "expectation": "every Observation.subject_reference resolves to a known patient",
      "failing_rows": 0,
      "passed": false,
      "duration_ms": 0,
      "error": null,
      "status": "pending — awaiting data generation",
      "count": null
    },
    {
      "id": "dq_ehr_004",
      "subdomain": "ehr_integrations",
      "table": "ehr_integrations.encounter",
      "column": "period_end",
      "rule_type": "range",
      "severity": "high",
      "expectation": "Encounter.period.end must be at or after period.start",
      "failing_rows": 0,
      "passed": false,
      "duration_ms": 0,
      "error": null,
      "status": "pending — awaiting data generation",
      "count": null
    },
    {
      "id": "dq_ehr_005",
      "subdomain": "ehr_integrations",
      "table": "ehr_integrations.condition",
      "column": "clinical_status_code",
      "rule_type": "distribution",
      "severity": "medium",
      "expectation": "Condition.clinicalStatus in FHIR-aligned enum",
      "failing_rows": 0,
      "passed": false,
      "duration_ms": 0,
      "error": null,
      "status": "pending — awaiting data generation",
      "count": null
    },
    {
      "id": "dq_cm_001",
      "subdomain": "capital_markets",
      "table": "capital_markets.trade",
      "column": "trade_id",
      "rule_type": "uniqueness",
      "severity": "critical",
      "expectation": "trade_id is unique",
      "failing_rows": 0,
      "passed": false,
      "duration_ms": 0,
      "error": null,
      "status": "pending — awaiting data generation",
      "count": null
    },
    {
      "id": "dq_cm_002",
      "subdomain": "capital_markets",
      "table": "capital_markets.execution",
      "column": "exec_type",
      "rule_type": "distribution",
      "severity": "high",
      "expectation": "FIX tag 150 ExecType in {F=Trade, 0=New, 5=Replaced, 4=Cancelled}",
      "failing_rows": 0,
      "passed": false,
      "duration_ms": 0,
      "error": null,
      "status": "pending — awaiting data generation",
      "count": null
    },
    {
      "id": "dq_cm_003",
      "subdomain": "capital_markets",
      "table": "capital_markets.execution",
      "column": "order_id",
      "rule_type": "foreign_key",
      "severity": "critical",
      "expectation": "every execution links to a known order",
      "failing_rows": 0,
      "passed": false,
      "duration_ms": 0,
      "error": null,
      "status": "pending — awaiting data generation",
      "count": null
    },
    {
      "id": "dq_cm_004",
      "subdomain": "capital_markets",
      "table": "capital_markets.trade",
      "column": "settlement_date",
      "rule_type": "range",
      "severity": "high",
      "expectation": "settlement_date is on or after trade_date",
      "failing_rows": 0,
      "passed": false,
      "duration_ms": 0,
      "error": null,
      "status": "pending — awaiting data generation",
      "count": null
    },
    {
      "id": "dq_ami_001",
      "subdomain": "smart_metering",
      "table": "smart_metering.meter_read",
      "column": "kwh_delivered",
      "rule_type": "range",
      "severity": "high",
      "expectation": "kwh_delivered is non-negative for every interval read",
      "failing_rows": 0,
      "passed": false,
      "duration_ms": 0,
      "error": null,
      "status": "pending — awaiting data generation",
      "count": null
    },
    {
      "id": "dq_ami_002",
      "subdomain": "smart_metering",
      "table": "smart_metering.meter_read",
      "column": "meter_id",
      "rule_type": "foreign_key",
      "severity": "critical",
      "expectation": "every meter_read.meter_id resolves in smart_metering.meter",
      "failing_rows": 0,
      "passed": false,
      "duration_ms": 0,
      "error": null,
      "status": "pending — awaiting data generation",
      "count": null
    },
    {
      "id": "dq_ami_003",
      "subdomain": "smart_metering",
      "table": "smart_metering.meter_read",
      "column": "quality_code",
      "rule_type": "distribution",
      "severity": "medium",
      "expectation": "C12.19 quality_code in {VALID, ESTIMATED, MISSING, EDITED}",
      "failing_rows": 0,
      "passed": false,
      "duration_ms": 0,
      "error": null,
      "status": "pending — awaiting data generation",
      "count": null
    },
    {
      "id": "dq_ami_004",
      "subdomain": "smart_metering",
      "table": "smart_metering.billing_determinant",
      "column": "period_end",
      "rule_type": "range",
      "severity": "high",
      "expectation": "billing period_end is strictly after period_start",
      "failing_rows": 0,
      "passed": false,
      "duration_ms": 0,
      "error": null,
      "status": "pending — awaiting data generation",
      "count": null
    },
    {
      "id": "dq_ct_001",
      "subdomain": "clinical_trials",
      "table": "clinical_trials.subject",
      "column": "usubjid",
      "rule_type": "uniqueness",
      "severity": "critical",
      "expectation": "SDTM USUBJID is unique within the demographics domain",
      "failing_rows": 0,
      "passed": false,
      "duration_ms": 0,
      "error": null,
      "status": "pending — awaiting data generation",
      "count": null
    },
    {
      "id": "dq_ct_002",
      "subdomain": "clinical_trials",
      "table": "clinical_trials.adverse_event",
      "column": "aeendtc",
      "rule_type": "range",
      "severity": "high",
      "expectation": "AE.aeendtc must be on or after AE.aestdtc when both populated",
      "failing_rows": 0,
      "passed": false,
      "duration_ms": 0,
      "error": null,
      "status": "pending — awaiting data generation",
      "count": null
    },
    {
      "id": "dq_ct_003",
      "subdomain": "clinical_trials",
      "table": "clinical_trials.adverse_event",
      "column": "aesev",
      "rule_type": "distribution",
      "severity": "medium",
      "expectation": "AE.aesev in {MILD, MODERATE, SEVERE, LIFE-THREATENING}",
      "failing_rows": 0,
      "passed": false,
      "duration_ms": 0,
      "error": null,
      "status": "pending — awaiting data generation",
      "count": null
    },
    {
      "id": "dq_ct_004",
      "subdomain": "clinical_trials",
      "table": "clinical_trials.visit",
      "column": "usubjid",
      "rule_type": "foreign_key",
      "severity": "critical",
      "expectation": "every SDTM SV row resolves to a subject in DM",
      "failing_rows": 0,
      "passed": false,
      "duration_ms": 0,
      "error": null,
      "status": "pending — awaiting data generation",
      "count": null
    },
    {
      "id": "dq_fo_001",
      "subdomain": "cloud_finops",
      "table": "cloud_finops.charge_record",
      "column": "billed_cost",
      "rule_type": "range",
      "severity": "high",
      "expectation": "FOCUS BilledCost cannot exceed ListCost (negative discount = data error)",
      "failing_rows": 0,
      "passed": false,
      "duration_ms": 0,
      "error": null,
      "status": "pending — awaiting data generation",
      "count": null
    },
    {
      "id": "dq_fo_002",
      "subdomain": "cloud_finops",
      "table": "cloud_finops.charge_record",
      "column": "billing_account_id",
      "rule_type": "foreign_key",
      "severity": "critical",
      "expectation": "every charge_record.billing_account_id resolves in billing_account",
      "failing_rows": 0,
      "passed": false,
      "duration_ms": 0,
      "error": null,
      "status": "pending — awaiting data generation",
      "count": null
    },
    {
      "id": "dq_fo_003",
      "subdomain": "cloud_finops",
      "table": "cloud_finops.resource_tag",
      "column": "tag_value",
      "rule_type": "not_null",
      "severity": "medium",
      "expectation": "tag_value populated (no untagged resources in the canonical tag table)",
      "failing_rows": 0,
      "passed": false,
      "duration_ms": 0,
      "error": null,
      "status": "pending — awaiting data generation",
      "count": null
    },
    {
      "id": "dq_fo_004",
      "subdomain": "cloud_finops",
      "table": "cloud_finops.charge_record",
      "column": "charge_period_end",
      "rule_type": "range",
      "severity": "high",
      "expectation": "charge_period_end is strictly after charge_period_start",
      "failing_rows": 0,
      "passed": false,
      "duration_ms": 0,
      "error": null,
      "status": "pending — awaiting data generation",
      "count": null
    },
    {
      "id": "dq_ev_001",
      "subdomain": "ev_charging",
      "table": "ev_charging.transaction",
      "column": "stopped_at",
      "rule_type": "range",
      "severity": "high",
      "expectation": "transaction.stopped_at is on or after started_at",
      "failing_rows": 0,
      "passed": false,
      "duration_ms": 0,
      "error": null,
      "status": "pending — awaiting data generation",
      "count": null
    },
    {
      "id": "dq_ev_002",
      "subdomain": "ev_charging",
      "table": "ev_charging.meter_value",
      "column": "energy_active_import_register_kwh",
      "rule_type": "range",
      "severity": "high",
      "expectation": "OCPP energy_active_import_register is non-negative",
      "failing_rows": 0,
      "passed": false,
      "duration_ms": 0,
      "error": null,
      "status": "pending — awaiting data generation",
      "count": null
    },
    {
      "id": "dq_ev_003",
      "subdomain": "ev_charging",
      "table": "ev_charging.transaction",
      "column": "connector_id",
      "rule_type": "foreign_key",
      "severity": "critical",
      "expectation": "every transaction.connector_id resolves in connector",
      "failing_rows": 0,
      "passed": false,
      "duration_ms": 0,
      "error": null,
      "status": "pending — awaiting data generation",
      "count": null
    },
    {
      "id": "dq_ev_004",
      "subdomain": "ev_charging",
      "table": "ev_charging.authorization",
      "column": "decision",
      "rule_type": "distribution",
      "severity": "medium",
      "expectation": "OCPP Authorize.decision in OCA-defined enum",
      "failing_rows": 0,
      "passed": false,
      "duration_ms": 0,
      "error": null,
      "status": "pending — awaiting data generation",
      "count": null
    },
    {
      "id": "dq_tax_001",
      "subdomain": "tax_administration",
      "table": "tax_administration.return",
      "column": "return_id",
      "rule_type": "uniqueness",
      "severity": "critical",
      "expectation": "return_id is unique within the filing system",
      "failing_rows": 0,
      "passed": false,
      "duration_ms": 0,
      "error": null,
      "status": "pending — awaiting data generation",
      "count": null
    },
    {
      "id": "dq_tax_002",
      "subdomain": "tax_administration",
      "table": "tax_administration.form",
      "column": "return_id",
      "rule_type": "foreign_key",
      "severity": "critical",
      "expectation": "every form.return_id resolves in tax_administration.return",
      "failing_rows": 0,
      "passed": false,
      "duration_ms": 0,
      "error": null,
      "status": "pending — awaiting data generation",
      "count": null
    },
    {
      "id": "dq_tax_003",
      "subdomain": "tax_administration",
      "table": "tax_administration.transmission",
      "column": "received_at",
      "rule_type": "range",
      "severity": "high",
      "expectation": "transmission.received_at is on or after sent_at",
      "failing_rows": 0,
      "passed": false,
      "duration_ms": 0,
      "error": null,
      "status": "pending — awaiting data generation",
      "count": null
    },
    {
      "id": "dq_tax_004",
      "subdomain": "tax_administration",
      "table": "tax_administration.fatca_account",
      "column": "account_balance_usd",
      "rule_type": "not_null",
      "severity": "medium",
      "expectation": "FATCA reportable accounts must carry a balance",
      "failing_rows": 0,
      "passed": false,
      "duration_ms": 0,
      "error": null,
      "status": "pending — awaiting data generation",
      "count": null
    },
    {
      "id": "dq_rwe_001",
      "subdomain": "real_world_evidence",
      "table": "real_world_evidence.person",
      "column": "gender_concept_id",
      "rule_type": "distribution",
      "severity": "medium",
      "expectation": "OMOP gender_concept_id in {8507=Male, 8532=Female, 0=Unknown}",
      "failing_rows": 0,
      "passed": false,
      "duration_ms": 0,
      "error": null,
      "status": "pending — awaiting data generation",
      "count": null
    },
    {
      "id": "dq_rwe_002",
      "subdomain": "real_world_evidence",
      "table": "real_world_evidence.condition_occurrence",
      "column": "person_id",
      "rule_type": "foreign_key",
      "severity": "critical",
      "expectation": "every condition_occurrence.person_id resolves in OMOP person",
      "failing_rows": 0,
      "passed": false,
      "duration_ms": 0,
      "error": null,
      "status": "pending — awaiting data generation",
      "count": null
    },
    {
      "id": "dq_rwe_003",
      "subdomain": "real_world_evidence",
      "table": "real_world_evidence.drug_exposure",
      "column": "drug_exposure_end_date",
      "rule_type": "range",
      "severity": "high",
      "expectation": "drug_exposure_end_date is on or after drug_exposure_start_date",
      "failing_rows": 0,
      "passed": false,
      "duration_ms": 0,
      "error": null,
      "status": "pending — awaiting data generation",
      "count": null
    },
    {
      "id": "dq_rwe_004",
      "subdomain": "real_world_evidence",
      "table": "real_world_evidence.visit_occurrence",
      "column": "visit_end_date",
      "rule_type": "range",
      "severity": "high",
      "expectation": "visit_end_date is on or after visit_start_date",
      "failing_rows": 0,
      "passed": false,
      "duration_ms": 0,
      "error": null,
      "status": "pending — awaiting data generation",
      "count": null
    },
    {
      "id": "dq_stl_001",
      "subdomain": "settlement_clearing",
      "table": "settlement_clearing.settlement_instruction",
      "column": "ssi_id",
      "rule_type": "uniqueness",
      "severity": "critical",
      "expectation": "ssi_id (sese.023 instruction id) is unique",
      "failing_rows": 0,
      "passed": false,
      "duration_ms": 0,
      "error": null,
      "status": "pending — awaiting data generation",
      "count": null
    },
    {
      "id": "dq_stl_002",
      "subdomain": "settlement_clearing",
      "table": "settlement_clearing.failed_settlement",
      "column": "fail_reason",
      "rule_type": "distribution",
      "severity": "medium",
      "expectation": "fail_reason in CSDR-aligned enum",
      "failing_rows": 0,
      "passed": false,
      "duration_ms": 0,
      "error": null,
      "status": "pending — awaiting data generation",
      "count": null
    },
    {
      "id": "dq_stl_003",
      "subdomain": "settlement_clearing",
      "table": "settlement_clearing.collateral_movement",
      "column": "quantity",
      "rule_type": "range",
      "severity": "high",
      "expectation": "collateral_movement.quantity strictly positive",
      "failing_rows": 0,
      "passed": false,
      "duration_ms": 0,
      "error": null,
      "status": "pending — awaiting data generation",
      "count": null
    },
    {
      "id": "dq_stl_004",
      "subdomain": "settlement_clearing",
      "table": "settlement_clearing.margin_call",
      "column": "due_at",
      "rule_type": "range",
      "severity": "high",
      "expectation": "margin_call.due_at is on or after issued_at",
      "failing_rows": 0,
      "passed": false,
      "duration_ms": 0,
      "error": null,
      "status": "pending — awaiting data generation",
      "count": null
    },
    {
      "id": "dq_prog_001",
      "subdomain": "programmatic_advertising",
      "table": "programmatic_advertising.bid",
      "column": "bid_price_cpm",
      "rule_type": "range",
      "severity": "high",
      "expectation": "bid price strictly positive — non-positive bids should never be persisted",
      "failing_rows": 0,
      "passed": false,
      "duration_ms": 0,
      "error": null,
      "status": "pending — awaiting data generation",
      "count": null
    },
    {
      "id": "dq_prog_002",
      "subdomain": "programmatic_advertising",
      "table": "programmatic_advertising.impression_event",
      "column": "viewable_pixels_pct",
      "rule_type": "range",
      "severity": "medium",
      "expectation": "MRC viewable_pixels_pct between 0 and 100",
      "failing_rows": 0,
      "passed": false,
      "duration_ms": 0,
      "error": null,
      "status": "pending — awaiting data generation",
      "count": null
    },
    {
      "id": "dq_prog_003",
      "subdomain": "programmatic_advertising",
      "table": "programmatic_advertising.conversion_event",
      "column": "click_event_id",
      "rule_type": "foreign_key",
      "severity": "critical",
      "expectation": "every conversion_event.click_event_id resolves in click_event",
      "failing_rows": 0,
      "passed": false,
      "duration_ms": 0,
      "error": null,
      "status": "pending — awaiting data generation",
      "count": null
    },
    {
      "id": "dq_prog_004",
      "subdomain": "programmatic_advertising",
      "table": "programmatic_advertising.bid",
      "column": "status",
      "rule_type": "distribution",
      "severity": "medium",
      "expectation": "bid.status in OpenRTB-aligned outcomes",
      "failing_rows": 0,
      "passed": false,
      "duration_ms": 0,
      "error": null,
      "status": "pending — awaiting data generation",
      "count": null
    }
  ]
}